pfreader/__init__.py
pfreader/__version__.py
pfreader/const.py
pfreader/core.py
pfreader/exceptions.py
pfreader/output.py
pfreader/pfreader.py
pfreader-0.0.6.dist-info/LICENSE
pfreader-0.0.6.dist-info/METADATA
pfreader-0.0.6.dist-info/WHEEL
pfreader-0.0.6.dist-info/top_level.txt
pfreader-0.0.6.dist-info/zip-safe
pfreader-0.0.6.dist-info/RECORD
