Metadata-Version: 2.1
Name: pfreader
Version: 0.0.6
Summary: Reader for Baxter® PrismaFlex® LOX files
Home-page: https://github.com/mpasternak/pfreader
Author: IPLWeb
Author-email: michal.dtz@gmail.com
License: MIT license
Keywords: PrismaFlex Baxter Prisma Flex Gambro LOX files CRRT CVVHDF TPE
Platform: UNKNOWN
Classifier: Development Status :: 2 - Pre-Alpha
Classifier: Intended Audience :: Developers
Classifier: License :: OSI Approved :: MIT License
Classifier: Natural Language :: English
Classifier: Programming Language :: Python :: 3
Classifier: Programming Language :: Python :: 3.6
Requires-Dist: et-xmlfile (==1.0.1)
Requires-Dist: jdcal (==1.4)
Requires-Dist: odfpy (==1.3.6)
Requires-Dist: openpyxl (==2.4.9)
Requires-Dist: pyyaml (==3.13)
Requires-Dist: tablib (==0.12.1)
Requires-Dist: unicodecsv (==0.14.1)
Requires-Dist: xlrd (==1.1.0)
Requires-Dist: xlwt (==1.3.0)
